sortz/__init__.py
sortz/__main__.py
sortz/bar.py
sortz/display.py
sortz/sorters.json
sortz/sorters.py
sortz/visualizer.py
sortz-1.1.1.dist-info/METADATA
sortz-1.1.1.dist-info/WHEEL
sortz-1.1.1.dist-info/entry_points.txt
sortz-1.1.1.dist-info/top_level.txt
sortz-1.1.1.dist-info/RECORD
