Metadata-Version: 2.1
Name: sortz
Version: 1.1.1
Summary: Visualize sorting algorithms
Home-page: https://github.com/MdeVillefort/sortz
Author: Monsieur de Villefort
Author-email: ethanmross92@gmail.com
License: UNKNOWN
Platform: UNKNOWN
Classifier: Programming Language :: Python :: 3
Classifier: Programming Language :: Python :: 3.8
Requires-Dist: pygame (==2.0.2)
